maltose/__init__.py
maltose/__version__.py
maltose/article/__init__.py
maltose/article/admin.py
maltose/article/apps.py
maltose/article/build.py
maltose/article/context_processors.py
maltose/article/forms.py
maltose/article/models.py
maltose/article/signals.py
maltose/article/tests.py
maltose/article/urls.py
maltose/article/management/__init__.py
maltose/article/management/commands/__init__.py
maltose/article/management/commands/import.py
maltose/article/management/commands/push.py
maltose/article/management/commands/update.py
maltose/article/migrations/0001_initial.py
maltose/article/migrations/__init__.py
maltose/article/views/__init__.py
maltose/article/views/api.py
maltose/article/views/view.py
maltose/editor/asset-manifest.json
maltose/editor/favicon.ico
maltose/editor/index.html
maltose/editor/manifest.json
maltose/editor/precache-manifest.f7019b14d5f5d95e64545166a760a11b.js
maltose/editor/service-worker.js
maltose/editor/static/css/2.15984d9f.chunk.css
maltose/editor/static/css/2.15984d9f.chunk.css.map
maltose/editor/static/css/main.84c36446.chunk.css
maltose/editor/static/css/main.84c36446.chunk.css.map
maltose/editor/static/js/1.75117139.chunk.js
maltose/editor/static/js/1.75117139.chunk.js.map
maltose/editor/static/js/2.1e870795.chunk.js
maltose/editor/static/js/2.1e870795.chunk.js.map
maltose/editor/static/js/main.d4aa6365.chunk.js
maltose/editor/static/js/main.d4aa6365.chunk.js.map
maltose/editor/static/js/runtime~main.e21c4546.js
maltose/editor/static/js/runtime~main.e21c4546.js.map
maltose/maltose/__init__.py
maltose/maltose/common.py
maltose/maltose/context_processors.py
maltose/maltose/dev.py
maltose/maltose/middleware.py
maltose/maltose/models.py
maltose/maltose/settings.py
maltose/maltose/urls.py
maltose/maltose/views.py
maltose/maltose/wsgi.py
maltose/maltose/management/__init__.py
maltose/maltose/management/commands/__init__.py
maltose/maltose/management/commands/clear_migrations.py
maltose/maltose/management/commands/preview.py
maltose-0.1.7.dist-info/LICENSE
maltose-0.1.7.dist-info/METADATA
maltose-0.1.7.dist-info/WHEEL
maltose-0.1.7.dist-info/entry_points.txt
maltose-0.1.7.dist-info/top_level.txt
maltose-0.1.7.dist-info/RECORD
