Metadata-Version: 2.1
Name: maltose
Version: 0.1.7
Summary: A static blog builder power by django
Home-page: https://github.com/MaltoseEditor/maltose
Author: AberSheeran
Author-email: abersheeran@qq.com
License: MIT
Platform: UNKNOWN
Classifier: License :: OSI Approved :: MIT License
Classifier: Programming Language :: Python :: 3.6
Requires-Python: >=3.6.0
Requires-Dist: Django
Requires-Dist: Pillow
Requires-Dist: Markdown
Requires-Dist: Pygments
Requires-Dist: colorama
